winregenv/__init__.py
winregenv/elevation_check.py
winregenv/expand_variable.py
winregenv/registry_base.py
winregenv/registry_context_managers.py
winregenv/registry_errors.py
winregenv/registry_interface.py
winregenv/registry_translation.py
winregenv/registry_types.py
winregenv/winapi.py
winregenv-0.2.0.dist-info/licenses/LICENSE
winregenv-0.2.0.dist-info/METADATA
winregenv-0.2.0.dist-info/WHEEL
winregenv-0.2.0.dist-info/top_level.txt
winregenv-0.2.0.dist-info/RECORD
