Metadata-Version: 2.4
Name: winregenv
Version: 0.2.0
Summary: A Pythonic, safer interface for common Windows Registry operations built on winreg.
Author: Travis Bender
License-Expression: MIT
Project-URL: Homepage, https://github.com/tgbender/winregenv
Project-URL: Repository, https://github.com/tgbender/winregenv
Keywords: windows,registry,winreg,environment,elevation,admin
Classifier: Development Status :: 3 - Alpha
Classifier: Intended Audience :: Developers
Classifier: Intended Audience :: System Administrators
Classifier: Operating System :: Microsoft :: Windows
Classifier: Programming Language :: Python :: 3
Classifier: Programming Language :: Python :: 3.8
Classifier: Programming Language :: Python :: 3.9
Classifier: Programming Language :: Python :: 3.10
Classifier: Programming Language :: Python :: 3.11
Classifier: Programming Language :: Python :: 3.12
Classifier: Topic :: System :: Systems Administration
Classifier: Topic :: Software Development :: Libraries :: Python Modules
Requires-Python: >=3.8
License-File: LICENSE
Provides-Extra: dev
Requires-Dist: pytest; extra == "dev"
Requires-Dist: pytest-mock; extra == "dev"
Dynamic: license-file
